setup.py
pyrabbit/__init__.py
pyrabbit/api.py
pyrabbit/http.py
pyrabbit.egg-info/PKG-INFO
pyrabbit.egg-info/SOURCES.txt
pyrabbit.egg-info/dependency_links.txt
pyrabbit.egg-info/not-zip-safe
pyrabbit.egg-info/requires.txt
pyrabbit.egg-info/top_level.txt